fireup/__init__.py
fireup/fireup.py
fireup/pyre/__init__.py
fireup/pyre/common.py
fireup/pyre/pyreup.py
fireup/pyre/pystorage.py
firebase_fireup-0.0.8.dist-info/METADATA
firebase_fireup-0.0.8.dist-info/WHEEL
firebase_fireup-0.0.8.dist-info/entry_points.txt
firebase_fireup-0.0.8.dist-info/top_level.txt
firebase_fireup-0.0.8.dist-info/RECORD
