Metadata-Version: 2.1
Name: firebase-fireup
Version: 0.0.8
Summary: Firebase Storage Uploader
Home-page: UNKNOWN
Author: Esa Firman
License: UNKNOWN
Platform: UNKNOWN
Classifier: Programming Language :: Python :: 3
Classifier: License :: OSI Approved :: MIT License
Classifier: Operating System :: OS Independent
Requires-Python: >=3.6
Requires-Dist: firebase-admin (==5.0.0)
Requires-Dist: requests (==2.25.1)
Requires-Dist: requests-toolbelt (==0.9.1)
Requires-Dist: python-jwt (==2.0.1)
